snscrape/__init__.py
snscrape/_cli.py
snscrape/base.py
snscrape/utils.py
snscrape/version.py
snscrape/modules/__init__.py
snscrape/modules/facebook.py
snscrape/modules/instagram.py
snscrape/modules/mastodon.py
snscrape/modules/reddit.py
snscrape/modules/telegram.py
snscrape/modules/twitter.py
snscrape/modules/vkontakte.py
snscrape/modules/weibo.py
snscrape-0.7.0.20230622.dist-info/LICENSE
snscrape-0.7.0.20230622.dist-info/METADATA
snscrape-0.7.0.20230622.dist-info/WHEEL
snscrape-0.7.0.20230622.dist-info/entry_points.txt
snscrape-0.7.0.20230622.dist-info/top_level.txt
snscrape-0.7.0.20230622.dist-info/RECORD
