Metadata-Version: 2.1
Name: snscrape
Version: 0.7.0.20230622
Summary: A social networking service scraper
Author: JustAnotherArchivist
Project-URL: repository, https://github.com/JustAnotherArchivist/snscrape
Classifier: Development Status :: 4 - Beta
Classifier: License :: OSI Approved :: GNU General Public License v3 or later (GPLv3+)
Classifier: Programming Language :: Python :: 3.8
Classifier: Programming Language :: Python :: 3.9
Classifier: Programming Language :: Python :: 3.10
Classifier: Programming Language :: Python :: 3.11
Requires-Python: ~=3.8
License-File: LICENSE
